rtl/params.vh
// ============================================
// params.vh — Centralized timing parameters
// FPGA-Based Traffic Light Controller
// ============================================
`ifndef PARAMS_VH
`define PARAMS_VH

`define T_GREEN_MIN_S   12   // Minimum green duration (seconds)
`define T_YELLOW_S       3   // Yellow light duration (seconds)
`define T_ALLRED_S       1   // All-red interlock (seconds)
`define T_WALK_S         8   // Pedestrian walk duration (seconds)
`define T_FLASH_TICKS    5   // Night mode flash half-period (ticks)

`endif

rtl/timer.v
// ============================================
// timer.v — Tick-driven countdown timer
// FSM uses this to time each traffic phase
// ============================================
module timer (
    input  wire        clk,
    input  wire        rst_n,
    input  wire        tick,
    input  wire        start,
    input  wire [15:0] ticks_to_run,
    output reg         busy
);

    reg [15:0] t;

    always @(posedge clk or negedge rst_n) begin
        if (!rst_n) begin
            t    <= 0;
            busy <= 0;
        end else if (start) begin
            t    <= ticks_to_run;
            busy <= 1;
        end else if (busy && tick) begin
            if (t == 0)
                busy <= 0;
            else
                t <= t - 1;
        end
    end

endmodule

rtl/traffic_fsm.v
// ============================================
// traffic_fsm.v — Moore FSM Traffic Controller
// States: NS_G, NS_Y, ALL_RED1, EW_G, EW_Y,
//         ALL_RED2, PED_WALK, PED_CLEAR,
//         EMERG_ALL_RED, NIGHT_FLASH
// ============================================
`include "rtl/params.vh"

module traffic_fsm #(
    parameter MAIN_IS_NS = 1,
    parameter TICK_HZ    = 10
)(
    input  wire clk,
    input  wire rst_n,
    input  wire tick,
    input  wire veh_ns,
    input  wire veh_ew,
    input  wire ped_pulse,
    input  wire emergency,
    input  wire night_mode,
    output reg  ns_g, ns_y, ns_r,
    output reg  ew_g, ew_y, ew_r,
    output reg  ped_walk, ped_dontwalk
);

    // ----------------------------------------
    // State encoding
    // ----------------------------------------
    localparam [3:0]
        S_NS_G         = 4'd0,
        S_NS_Y         = 4'd1,
        S_ALL_RED1     = 4'd2,
        S_EW_G         = 4'd3,
        S_EW_Y         = 4'd4,
        S_ALL_RED2     = 4'd5,
        S_PED_WALK     = 4'd6,
        S_PED_CLEAR    = 4'd7,
        S_EMERG        = 4'd8,
        S_NIGHT        = 4'd9;

    reg [3:0] state, next_state;

    // ----------------------------------------
    // Timer wires
    // ----------------------------------------
    reg        start_t;
    reg [15:0] ticks_load;
    wire       busy;

    timer u_timer (
        .clk          (clk),
        .rst_n        (rst_n),
        .tick         (tick),
        .start        (start_t),
        .ticks_to_run (ticks_load),
        .busy         (busy)
    );

    // ----------------------------------------
    // Seconds → ticks conversion
    // ----------------------------------------
    function [15:0] SEC;
        input integer s;
        SEC = s * TICK_HZ;
    endfunction

    // ----------------------------------------
    // Pedestrian request latch
    // ----------------------------------------
    reg ped_req;
    always @(posedge clk or negedge rst_n) begin
        if (!rst_n)
            ped_req <= 1'b0;
        else if (ped_pulse)
            ped_req <= 1'b1;
        else if (state == S_PED_CLEAR)
            ped_req <= 1'b0;
    end

    // ----------------------------------------
    // Night flash toggle (uses tick)
    // ----------------------------------------
    reg flash;
    reg [3:0] flash_cnt;
    always @(posedge clk or negedge rst_n) begin
        if (!rst_n) begin
            flash     <= 0;
            flash_cnt <= 0;
        end else if (tick) begin
            if (flash_cnt == `T_FLASH_TICKS - 1) begin
                flash     <= ~flash;
                flash_cnt <= 0;
            end else begin
                flash_cnt <= flash_cnt + 1;
            end
        end
    end

    // ----------------------------------------
    // State register
    // ----------------------------------------
    always @(posedge clk or negedge rst_n) begin
        if (!rst_n)
            state <= S_NS_G;
        else if (emergency)
            state <= S_EMERG;
        else if (night_mode)
            state <= S_NIGHT;
        else
            state <= next_state;
    end

    // ----------------------------------------
    // Next-state logic + timer control
    // ----------------------------------------
    always @(*) begin
        // defaults
        next_state = state;
        start_t    = 1'b0;
        ticks_load = 16'd0;

        // output defaults — all red safe state
        ns_g = 0; ns_y = 0; ns_r = 1;
        ew_g = 0; ew_y = 0; ew_r = 1;
        ped_walk = 0; ped_dontwalk = 1;

        case (state)

            S_NS_G: begin
                ns_g = 1; ns_r = 0;
                ew_r = 1;
                if (!busy) begin
                    start_t    = 1'b1;
                    ticks_load = SEC(`T_GREEN_MIN_S);
                end
                if (!busy && (ped_req || veh_ew))
                    next_state = S_NS_Y;
            end

            S_NS_Y: begin
                ns_y = 1; ns_r = 0;
                ew_r = 1;
                if (!busy) begin
                    start_t    = 1'b1;
                    ticks_load = SEC(`T_YELLOW_S);
                end
                if (!busy && ticks_load == 0)
                    next_state = S_ALL_RED1;
            end

            S_ALL_RED1: begin
                ns_r = 1; ew_r = 1;
                if (!busy) begin
                    start_t    = 1'b1;
                    ticks_load = SEC(`T_ALLRED_S);
                end
                if (!busy && ticks_load == 0)
                    next_state = ped_req ? S_PED_WALK : S_EW_G;
            end

            S_EW_G: begin
                ew_g = 1; ew_r = 0;
                ns_r = 1;
                if (!busy) begin
                    start_t    = 1'b1;
                    ticks_load = SEC(`T_GREEN_MIN_S);
                end
                if (!busy && (ped_req || veh_ns))
                    next_state = S_EW_Y;
            end

            S_EW_Y: begin
                ew_y = 1; ew_r = 0;
                ns_r = 1;
                if (!busy) begin
                    start_t    = 1'b1;
                    ticks_load = SEC(`T_YELLOW_S);
                end
                if (!busy && ticks_load == 0)
                    next_state = S_ALL_RED2;
            end

            S_ALL_RED2: begin
                ns_r = 1; ew_r = 1;
                if (!busy) begin
                    start_t    = 1'b1;
                    ticks_load = SEC(`T_ALLRED_S);
                end
                if (!busy && ticks_load == 0)
                    next_state = ped_req ? S_PED_WALK : S_NS_G;
            end

            S_PED_WALK: begin
                ns_r = 1; ew_r = 1;
                ped_walk = 1; ped_dontwalk = 0;
                if (!busy) begin
                    start_t    = 1'b1;
                    ticks_load = SEC(`T_WALK_S);
                end
                if (!busy && ticks_load == 0)
                    next_state = S_PED_CLEAR;
            end

            S_PED_CLEAR: begin
                ns_r = 1; ew_r = 1;
                ped_dontwalk = 1;
                if (!busy) begin
                    start_t    = 1'b1;
                    ticks_load = SEC(`T_ALLRED_S);
                end
                if (!busy && ticks_load == 0)
                    next_state = S_NS_G;
            end

            S_EMERG: begin
                ns_r = 1; ew_r = 1;
                ped_dontwalk = 1;
                // hold until emergency deasserts
                // state register returns to S_NS_G on next cycle
            end

            S_NIGHT: begin
                ped_dontwalk = 1;
                if (MAIN_IS_NS) begin
                    ns_y = flash;
                    ns_r = ~flash;
                    ew_r =  flash;
                    ew_y = ~flash;
                end else begin
                    ew_y =  flash;
                    ew_r = ~flash;
                    ns_r =  flash;
                    ns_y = ~flash;
                end
            end

            default: begin
                ns_r = 1; ew_r = 1;
                next_state = S_NS_G;
            end

        endcase
    end

endmodule

rtl/debounce_sync.v
// ============================================
// debounce_sync.v — 2FF Synchronizer + Debounce
// Cleans async button/sensor inputs
// ============================================
module debounce_sync #(
    parameter integer TICKS = 5   // stable ticks needed
)(
    input  wire clk,
    input  wire rst_n,
    input  wire tick,
    input  wire async_in,
    output reg  pulse,            // 1-tick pulse on rising edge
    output reg  level             // debounced level
);

    // 2-FF synchronizer
    reg s1, s2;
    always @(posedge clk) begin
        s1 <= async_in;
        s2 <= s1;
    end

    // Debounce counter
    reg [$clog2(TICKS+1)-1:0] db;
    reg stable;

    always @(posedge clk or negedge rst_n) begin
        if (!rst_n) begin
            db     <= 0;
            stable <= 0;
            level  <= 0;
            pulse  <= 0;
        end else begin
            pulse <= 0;
            if (tick) begin
                if (s2 != stable) begin
                    db <= db + 1;
                    if (db == TICKS) begin
                        stable <= s2;
                        db     <= 0;
                    end
                end else begin
                    db <= 0;
                end
                if (stable && !level) begin
                    level <= 1;
                    pulse <= 1;
                end else if (!stable) begin
                    level <= 0;
                end
            end
        end
    end

endmodule

rtl/clk_en.v
// ============================================
// clk_en.v — Clock Enable Divider
// Generates a 10Hz tick from 50MHz FPGA clock
// Single clock domain — no gated clocks
// ============================================
module clk_en #(
    parameter integer CLK_HZ  = 50_000_000,
    parameter integer TICK_HZ = 10
)(
    input  wire clk,
    input  wire rst_n,
    output reg  tick
);

    localparam integer DIV = CLK_HZ / TICK_HZ;
    reg [$clog2(DIV)-1:0] cnt;

    always @(posedge clk or negedge rst_n) begin
        if (!rst_n) begin
            cnt  <= 0;
            tick <= 1'b0;
        end else begin
            tick <= 1'b0;
            if (cnt == DIV - 1) begin
                cnt  <= 0;
                tick <= 1'b1;
            end else begin
                cnt <= cnt + 1'b1;
            end
        end
    end

endmodule

rtl/top.v
// ============================================
// top.v — Top-level integration module
// Wires: tick gen → debouncers → FSM → outputs
// ============================================
module top (
    input  wire clk_50m,
    input  wire rst_btn,
    input  wire veh_ns_raw,
    input  wire veh_ew_raw,
    input  wire ped_btn_raw,
    input  wire emergency_raw,
    input  wire night_raw,
    output wire NS_G, NS_Y, NS_R,
    output wire EW_G, EW_Y, EW_R,
    output wire PED_WALK, PED_DONT
);

    wire rst_n = ~rst_btn;

    // 10 Hz tick
    wire tick;
    clk_en #(.CLK_HZ(50_000_000), .TICK_HZ(10)) u_tick (
        .clk   (clk_50m),
        .rst_n (rst_n),
        .tick  (tick)
    );

    // Debounce all inputs
    wire ped_pulse, ped_level;
    wire em_level, night_level;
    wire vns_level, vew_level;

    debounce_sync #(.TICKS(3)) u_ped (
        .clk(clk_50m), .rst_n(rst_n), .tick(tick),
        .async_in(ped_btn_raw), .pulse(ped_pulse), .level(ped_level)
    );
    debounce_sync #(.TICKS(1)) u_em (
        .clk(clk_50m), .rst_n(rst_n), .tick(tick),
        .async_in(emergency_raw), .pulse(), .level(em_level)
    );
    debounce_sync #(.TICKS(1)) u_ng (
        .clk(clk_50m), .rst_n(rst_n), .tick(tick),
        .async_in(night_raw), .pulse(), .level(night_level)
    );
    debounce_sync #(.TICKS(1)) u_vns (
        .clk(clk_50m), .rst_n(rst_n), .tick(tick),
        .async_in(veh_ns_raw), .pulse(), .level(vns_level)
    );
    debounce_sync #(.TICKS(1)) u_vew (
        .clk(clk_50m), .rst_n(rst_n), .tick(tick),
        .async_in(veh_ew_raw), .pulse(), .level(vew_level)
    );

    // FSM
    traffic_fsm #(.MAIN_IS_NS(1), .TICK_HZ(10)) u_fsm (
        .clk        (clk_50m),
        .rst_n      (rst_n),
        .tick       (tick),
        .veh_ns     (vns_level),
        .veh_ew     (vew_level),
        .ped_pulse  (ped_pulse),
        .emergency  (em_level),
        .night_mode (night_level),
        .ns_g(NS_G), .ns_y(NS_Y), .ns_r(NS_R),
        .ew_g(EW_G), .ew_y(EW_Y), .ew_r(EW_R),
        .ped_walk(PED_WALK), .ped_dontwalk(PED_DONT)
    );

endmodule

tb/traffic_tb.v
// ============================================
// traffic_tb.v — Testbench
// Accelerated simulation (small CLK_HZ)
// Tests: normal cycle, pedestrian, emergency,
//        night mode, conflict detection
// ============================================
`timescale 1ns/1ps

module traffic_tb;

    // ----------------------------------------
    // DUT signals
    // ----------------------------------------
    reg clk   = 0;
    reg rst_btn = 1;
    reg veh_ns  = 0;
    reg veh_ew  = 0;
    reg ped     = 0;
    reg emer    = 0;
    reg night   = 0;

    wire NS_G, NS_Y, NS_R;
    wire EW_G, EW_Y, EW_R;
    wire PW, PD;

    // ----------------------------------------
    // Instantiate top with SMALL clock
    // so simulation finishes fast
    // ----------------------------------------
    top #() DUT (
        .clk_50m      (clk),
        .rst_btn      (rst_btn),
        .veh_ns_raw   (veh_ns),
        .veh_ew_raw   (veh_ew),
        .ped_btn_raw  (ped),
        .emergency_raw(emer),
        .night_raw    (night),
        .NS_G(NS_G), .NS_Y(NS_Y), .NS_R(NS_R),
        .EW_G(EW_G), .EW_Y(EW_Y), .EW_R(EW_R),
        .PED_WALK(PW), .PED_DONT(PD)
    );

    // 100 MHz sim clock (10ns period)
    always #5 clk = ~clk;

    // ----------------------------------------
    // Safety checker — NEVER both green
    // ----------------------------------------
    always @(posedge clk) begin
        if (NS_G && EW_G) begin
            $display("❌ FATAL: NS_G and EW_G both HIGH at time %0t", $time);
            $finish;
        end
    end

    // ----------------------------------------
    // Monitor — print state changes
    // ----------------------------------------
    always @(NS_G or NS_Y or NS_R or EW_G or EW_Y or EW_R or PW) begin
        $display("T=%0t | NS[G=%b Y=%b R=%b] EW[G=%b Y=%b R=%b] PED_WALK=%b",
            $time, NS_G, NS_Y, NS_R, EW_G, EW_Y, EW_R, PW);
    end

    // ----------------------------------------
    // Stimulus
    // ----------------------------------------
    initial begin
        // Save waveform
        $dumpfile("simulation/traffic.vcd");
        $dumpvars(0, traffic_tb);

        $display("=== FPGA Traffic Light Controller Simulation ===");

        // Release reset after 100ns
        #100 rst_btn = 0;
        $display(">> Reset released — Normal cycle starting");

        // Let NS green run for a while
        #5000;

        // EW vehicle arrives — triggers NS→yellow transition
        $display(">> EW vehicle detected");
        veh_ew = 1;
        #3000 veh_ew = 0;

        // Pedestrian button press
        #5000;
        $display(">> Pedestrian button pressed");
        ped = 1;
        #500 ped = 0;

        // Let pedestrian walk phase complete
        #15000;

        // Emergency vehicle!
        $display(">> EMERGENCY triggered — All RED");
        emer = 1;
        #8000 emer = 0;
        $display(">> Emergency cleared — resuming");

        // Night mode
        #10000;
        $display(">> Night mode ON");
        night = 1;
        #10000 night = 0;
        $display(">> Night mode OFF — resuming normal");

        // Let it run a bit more
        #20000;

        $display("=== Simulation Complete — No conflicts detected ✅ ===");
        $finish;
    end

endmodule

simulation/traffic.vcd
$date
	Tue Jun 16 23:13:58 2026
$end
$version
	Icarus Verilog
$end
$timescale
	1ps
$end
$scope module traffic_tb $end
$var wire 1 ! PW $end
$var wire 1 " PD $end
$var wire 1 # NS_Y $end
$var wire 1 $ NS_R $end
$var wire 1 % NS_G $end
$var wire 1 & EW_Y $end
$var wire 1 ' EW_R $end
$var wire 1 ( EW_G $end
$var reg 1 ) clk $end
$var reg 1 * emer $end
$var reg 1 + night $end
$var reg 1 , ped $end
$var reg 1 - rst_btn $end
$var reg 1 . veh_ew $end
$var reg 1 / veh_ns $end
$scope module DUT $end
$var wire 1 ) clk_50m $end
$var wire 1 * emergency_raw $end
$var wire 1 + night_raw $end
$var wire 1 , ped_btn_raw $end
$var wire 1 - rst_btn $end
$var wire 1 0 rst_n $end
$var wire 1 . veh_ew_raw $end
$var wire 1 / veh_ns_raw $end
$var wire 1 1 vns_level $end
$var wire 1 2 vew_level $end
$var wire 1 3 tick $end
$var wire 1 4 ped_pulse $end
$var wire 1 5 ped_level $end
$var wire 1 6 night_level $end
$var wire 1 7 em_level $end
$var wire 1 ! PED_WALK $end
$var wire 1 " PED_DONT $end
$var wire 1 # NS_Y $end
$var wire 1 $ NS_R $end
$var wire 1 % NS_G $end
$var wire 1 & EW_Y $end
$var wire 1 ' EW_R $end
$var wire 1 ( EW_G $end
$scope module u_em $end
$var wire 1 * async_in $end
$var wire 1 ) clk $end
$var wire 1 0 rst_n $end
$var wire 1 3 tick $end
$var parameter 32 8 TICKS $end
$var reg 1 9 db $end
$var reg 1 7 level $end
$var reg 1 : pulse $end
$var reg 1 ; s1 $end
$var reg 1 < s2 $end
$var reg 1 = stable $end
$upscope $end
$scope module u_fsm $end
$var wire 1 ) clk $end
$var wire 1 7 emergency $end
$var wire 1 0 rst_n $end
$var wire 1 1 veh_ns $end
$var wire 1 2 veh_ew $end
$var wire 1 3 tick $end
$var wire 1 4 ped_pulse $end
$var wire 1 6 night_mode $end
$var wire 1 > busy $end
$var parameter 32 ? MAIN_IS_NS $end
$var parameter 4 @ S_ALL_RED1 $end
$var parameter 4 A S_ALL_RED2 $end
$var parameter 4 B S_EMERG $end
$var parameter 4 C S_EW_G $end
$var parameter 4 D S_EW_Y $end
$var parameter 4 E S_NIGHT $end
$var parameter 4 F S_NS_G $end
$var parameter 4 G S_NS_Y $end
$var parameter 4 H S_PED_CLEAR $end
$var parameter 4 I S_PED_WALK $end
$var parameter 32 J TICK_HZ $end
$var reg 1 ( ew_g $end
$var reg 1 ' ew_r $end
$var reg 1 & ew_y $end
$var reg 1 K flash $end
$var reg 4 L flash_cnt [3:0] $end
$var reg 4 M next_state [3:0] $end
$var reg 1 % ns_g $end
$var reg 1 $ ns_r $end
$var reg 1 # ns_y $end
$var reg 1 " ped_dontwalk $end
$var reg 1 N ped_req $end
$var reg 1 ! ped_walk $end
$var reg 1 O start_t $end
$var reg 4 P state [3:0] $end
$var reg 16 Q ticks_load [15:0] $end
$scope function SEC $end
$var integer 32 R s [31:0] $end
$upscope $end
$scope module u_timer $end
$var wire 1 ) clk $end
$var wire 1 0 rst_n $end
$var wire 1 O start $end
$var wire 16 S ticks_to_run [15:0] $end
$var wire 1 3 tick $end
$var reg 1 > busy $end
$var reg 16 T t [15:0] $end
$upscope $end
$upscope $end
$scope module u_ng $end
$var wire 1 + async_in $end
$var wire 1 ) clk $end
$var wire 1 0 rst_n $end
$var wire 1 3 tick $end
$var parameter 32 U TICKS $end
$var reg 1 V db $end
$var reg 1 6 level $end
$var reg 1 W pulse $end
$var reg 1 X s1 $end
$var reg 1 Y s2 $end
$var reg 1 Z stable $end
$upscope $end
$scope module u_ped $end
$var wire 1 , async_in $end
$var wire 1 ) clk $end
$var wire 1 0 rst_n $end
$var wire 1 3 tick $end
$var parameter 32 [ TICKS $end
$var reg 2 \ db [1:0] $end
$var reg 1 5 level $end
$var reg 1 4 pulse $end
$var reg 1 ] s1 $end
$var reg 1 ^ s2 $end
$var reg 1 _ stable $end
$upscope $end
$scope module u_tick $end
$var wire 1 ) clk $end
$var wire 1 0 rst_n $end
$var parameter 32 ` CLK_HZ $end
$var parameter 32 a DIV $end
$var parameter 32 b TICK_HZ $end
$var reg 23 c cnt [22:0] $end
$var reg 1 3 tick $end
$upscope $end
$scope module u_vew $end
$var wire 1 . async_in $end
$var wire 1 ) clk $end
$var wire 1 0 rst_n $end
$var wire 1 3 tick $end
$var parameter 32 d TICKS $end
$var reg 1 e db $end
$var reg 1 2 level $end
$var reg 1 f pulse $end
$var reg 1 g s1 $end
$var reg 1 h s2 $end
$var reg 1 i stable $end
$upscope $end
$scope module u_vns $end
$var wire 1 / async_in $end
$var wire 1 ) clk $end
$var wire 1 0 rst_n $end
$var wire 1 3 tick $end
$var parameter 32 j TICKS $end
$var reg 1 k db $end
$var reg 1 1 level $end
$var reg 1 l pulse $end
$var reg 1 m s1 $end
$var reg 1 n s2 $end
$var reg 1 o stable $end
$upscope $end
$upscope $end
$upscope $end
$enddefinitions $end
$comment Show the parameter values. $end
$dumpall
b1 j
b1 d
b1010 b
b10011000100101101000000 a
b10111110101111000010000000 `
b11 [
b1 U
b1010 J
b110 I
b111 H
b1 G
b0 F
b1001 E
b100 D
b11 C
b1000 B
b101 A
b10 @
b1 ?
b1 8
$end
#0
$dumpvars
xo
xn
xm
xl
xk
xi
xh
xg
xf
xe
bx c
x_
x^
x]
bx \
xZ
xY
xX
xW
xV
bx T
bx S
bx R
bx Q
bx P
xO
xN
bx M
bx L
xK
x>
x=
x<
x;
x:
x9
x7
x6
x5
x4
x3
x2
x1
00
0/
0.
1-
0,
0+
0*
0)
x(
x'
x&
x%
x$
x#
x"
x!
$end
#5000
b1100 R
1"
0!
1'
0&
0(
0$
0#
1%
b1111000 Q
b1111000 S
1O
b0 M
03
b0 c
04
05
0_
b0 \
0:
07
0=
09
0W
06
0Z
0V
0l
01
0o
0k
0f
02
0i
0e
0>
b0 T
0N
b0 L
0K
b0 P
0]
0;
0X
0m
0g
1)
#10000
0)
#15000
0h
0n
0Y
0<
0^
1)
#20000
0)
#25000
1)
#30000
0)
#35000
1)
#40000
0)
#45000
1)
#50000
0)
#55000
1)
#60000
0)
#65000
1)
#70000
0)
#75000
1)
#80000
0)
#85000
1)
#90000
0)
#95000
1)
#100000
10
0)
0-
#105000
0$
1%
b0 Q
b0 S
0O
b1 c
1>
b1111000 T
1)
#110000
0)
#115000
b10 c
1)
#120000
0)
#125000
b11 c
1)
#130000
0)
#135000
b100 c
1)
#140000
0)
#145000
b101 c
1)
#150000
0)
#155000
b110 c
1)
#160000
0)
#165000
b111 c
1)
#170000
0)
#175000
b1000 c
1)
#180000
0)
#185000
b1001 c
1)
#190000
0)
#195000
b1010 c
1)
#200000
0)
#205000
b1011 c
1)
#210000
0)
#215000
b1100 c
1)
#220000
0)
#225000
b1101 c
1)
#230000
0)
#235000
b1110 c
1)
#240000
0)
#245000
b1111 c
1)
#250000
0)
#255000
b10000 c
1)
#260000
0)
#265000
b10001 c
1)
#270000
0)
#275000
b10010 c
1)
#280000
0)
#285000
b10011 c
1)
#290000
0)
#295000
b10100 c
1)
#300000
0)
#305000
b10101 c
1)
#310000
0)
#315000
b10110 c
1)
#320000
0)
#325000
b10111 c
1)
#330000
0)
#335000
b11000 c
1)
#340000
0)
#345000
b11001 c
1)
#350000
0)
#355000
b11010 c
1)
#360000
0)
#365000
b11011 c
1)
#370000
0)
#375000
b11100 c
1)
#380000
0)
#385000
b11101 c
1)
#390000
0)
#395000
b11110 c
1)
#400000
0)
#405000
b11111 c
1)
#410000
0)
#415000
b100000 c
1)
#420000
0)
#425000
b100001 c
1)
#430000
0)
#435000
b100010 c
1)
#440000
0)
#445000
b100011 c
1)
#450000
0)
#455000
b100100 c
1)
#460000
0)
#465000
b100101 c
1)
#470000
0)
#475000
b100110 c
1)
#480000
0)
#485000
b100111 c
1)
#490000
0)
#495000
b101000 c
1)
#500000
0)
#505000
b101001 c
1)
#510000
0)
#515000
b101010 c
1)
#520000
0)
#525000
b101011 c
1)
#530000
0)
#535000
b101100 c
1)
#540000
0)
#545000
b101101 c
1)
#550000
0)
#555000
b101110 c
1)
#560000
0)
#565000
b101111 c
1)
#570000
0)
#575000
b110000 c
1)
#580000
0)
#585000
b110001 c
1)
#590000
0)
#595000
b110010 c
1)
#600000
0)
#605000
b110011 c
1)
#610000
0)
#615000
b110100 c
1)
#620000
0)
#625000
b110101 c
1)
#630000
0)
#635000
b110110 c
1)
#640000
0)
#645000
b110111 c
1)
#650000
0)
#655000
b111000 c
1)
#660000
0)
#665000
b111001 c
1)
#670000
0)
#675000
b111010 c
1)
#680000
0)
#685000
b111011 c
1)
#690000
0)
#695000
b111100 c
1)
#700000
0)
#705000
b111101 c
1)
#710000
0)
#715000
b111110 c
1)
#720000
0)
#725000
b111111 c
1)
#730000
0)
#735000
b1000000 c
1)
#740000
0)
#745000
b1000001 c
1)
#750000
0)
#755000
b1000010 c
1)
#760000
0)
#765000
b1000011 c
1)
#770000
0)
#775000
b1000100 c
1)
#780000
0)
#785000
b1000101 c
1)
#790000
0)
#795000
b1000110 c
1)
#800000
0)
#805000
b1000111 c
1)
#810000
0)
#815000
b1001000 c
1)
#820000
0)
#825000
b1001001 c
1)
#830000
0)
#835000
b1001010 c
1)
#840000
0)
#845000
b1001011 c
1)
#850000
0)
#855000
b1001100 c
1)
#860000
0)
#865000
b1001101 c
1)
#870000
0)
#875000
b1001110 c
1)
#880000
0)
#885000
b1001111 c
1)
#890000
0)
#895000
b1010000 c
1)
#900000
0)
#905000
b1010001 c
1)
#910000
0)
#915000
b1010010 c
1)
#920000
0)
#925000
b1010011 c
1)
#930000
0)
#935000
b1010100 c
1)
#940000
0)
#945000
b1010101 c
1)
#950000
0)
#955000
b1010110 c
1)
#960000
0)
#965000
b1010111 c
1)
#970000
0)
#975000
b1011000 c
1)
#980000
0)
#985000
b1011001 c
1)
#990000
0)
#995000
b1011010 c
1)
#1000000
0)
#1005000
b1011011 c
1)
#1010000
0)
#1015000
b1011100 c
1)
#1020000
0)
#1025000
b1011101 c
1)
#1030000
0)
#1035000
b1011110 c
1)
#1040000
0)
#1045000
b1011111 c
1)
#1050000
0)
#1055000
b1100000 c
1)
#1060000
0)
#1065000
b1100001 c
1)
#1070000
0)
#1075000
b1100010 c
1)
#1080000
0)
#1085000
b1100011 c
1)
#1090000
0)
#1095000
b1100100 c
1)
#1100000
0)
#1105000
b1100101 c
1)
#1110000
0)
#1115000
b1100110 c
1)
#1120000
0)
#1125000
b1100111 c
1)
#1130000
0)
#1135000
b1101000 c
1)
#1140000
0)
#1145000
b1101001 c
1)
#1150000
0)
#1155000
b1101010 c
1)
#1160000
0)
#1165000
b1101011 c
1)
#1170000
0)
#1175000
b1101100 c
1)
#1180000
0)
#1185000
b1101101 c
1)
#1190000
0)
#1195000
b1101110 c
1)
#1200000
0)
#1205000
b1101111 c
1)
#1210000
0)
#1215000
b1110000 c
1)
#1220000
0)
#1225000
b1110001 c
1)
#1230000
0)
#1235000
b1110010 c
1)
#1240000
0)
#1245000
b1110011 c
1)
#1250000
0)
#1255000
b1110100 c
1)
#1260000
0)
#1265000
b1110101 c
1)
#1270000
0)
#1275000
b1110110 c
1)
#1280000
0)
#1285000
b1110111 c
1)
#1290000
0)
#1295000
b1111000 c
1)
#1300000
0)
#1305000
b1111001 c
1)
#1310000
0)
#1315000
b1111010 c
1)
#1320000
0)
#1325000
b1111011 c
1)
#1330000
0)
#1335000
b1111100 c
1)
#1340000
0)
#1345000
b1111101 c
1)
#1350000
0)
#1355000
b1111110 c
1)
#1360000
0)
#1365000
b1111111 c
1)
#1370000
0)
#1375000
b10000000 c
1)
#1380000
0)
#1385000
b10000001 c
1)
#1390000
0)
#1395000
b10000010 c
1)
#1400000
0)
#1405000
b10000011 c
1)
#1410000
0)
#1415000
b10000100 c
1)
#1420000
0)
#1425000
b10000101 c
1)
#1430000
0)
#1435000
b10000110 c
1)
#1440000
0)
#1445000
b10000111 c
1)
#1450000
0)
#1455000
b10001000 c
1)
#1460000
0)
#1465000
b10001001 c
1)
#1470000
0)
#1475000
b10001010 c
1)
#1480000
0)
#1485000
b10001011 c
1)
#1490000
0)
#1495000
b10001100 c
1)
#1500000
0)
#1505000
b10001101 c
1)
#1510000
0)
#1515000
b10001110 c
1)
#1520000
0)
#1525000
b10001111 c
1)
#1530000
0)
#1535000
b10010000 c
1)
#1540000
0)
#1545000
b10010001 c
1)
#1550000
0)
#1555000
b10010010 c
1)
#1560000
0)
#1565000
b10010011 c
1)
#1570000
0)
#1575000
b10010100 c
1)
#1580000
0)
#1585000
b10010101 c
1)
#1590000
0)
#1595000
b10010110 c
1)
#1600000
0)
#1605000
b10010111 c
1)
#1610000
0)
#1615000
b10011000 c
1)
#1620000
0)
#1625000
b10011001 c
1)
#1630000
0)
#1635000
b10011010 c
1)
#1640000
0)
#1645000
b10011011 c
1)
#1650000
0)
#1655000
b10011100 c
1)
#1660000
0)
#1665000
b10011101 c
1)
#1670000
0)
#1675000
b10011110 c
1)
#1680000
0)
#1685000
b10011111 c
1)
#1690000
0)
#1695000
b10100000 c
1)
#1700000
0)
#1705000
b10100001 c
1)
#1710000
0)
#1715000
b10100010 c
1)
#1720000
0)
#1725000
b10100011 c
1)
#1730000
0)
#1735000
b10100100 c
1)
#1740000
0)
#1745000
b10100101 c
1)
#1750000
0)
#1755000
b10100110 c
1)
#1760000
0)
#1765000
b10100111 c
1)
#1770000
0)
#1775000
b10101000 c
1)
#1780000
0)
#1785000
b10101001 c
1)
#1790000
0)
#1795000
b10101010 c
1)
#1800000
0)
#1805000
b10101011 c
1)
#1810000
0)
#1815000
b10101100 c
1)
#1820000
0)
#1825000
b10101101 c
1)
#1830000
0)
#1835000
b10101110 c
1)
#1840000
0)
#1845000
b10101111 c
1)
#1850000
0)
#1855000
b10110000 c
1)
#1860000
0)
#1865000
b10110001 c
1)
#1870000
0)
#1875000
b10110010 c
1)
#1880000
0)
#1885000
b10110011 c
1)
#1890000
0)
#1895000
b10110100 c
1)
#1900000
0)
#1905000
b10110101 c
1)
#1910000
0)
#1915000
b10110110 c
1)
#1920000
0)
#1925000
b10110111 c
1)
#1930000
0)
#1935000
b10111000 c
1)
#1940000
0)
#1945000
b10111001 c
1)
#1950000
0)
#1955000
b10111010 c
1)
#1960000
0)
#1965000
b10111011 c
1)
#1970000
0)
#1975000
b10111100 c
1)
#1980000
0)
#1985000
b10111101 c
1)
#1990000
0)
#1995000
b10111110 c
1)
#2000000
0)
#2005000
b10111111 c
1)
#2010000
0)
#2015000
b11000000 c
1)
#2020000
0)
#2025000
b11000001 c
1)
#2030000
0)
#2035000
b11000010 c
1)
#2040000
0)
#2045000
b11000011 c
1)
#2050000
0)
#2055000
b11000100 c
1)
#2060000
0)
#2065000
b11000101 c
1)
#2070000
0)
#2075000
b11000110 c
1)
#2080000
0)
#2085000
b11000111 c
1)
#2090000
0)
#2095000
b11001000 c
1)
#2100000
0)
#2105000
b11001001 c
1)
#2110000
0)
#2115000
b11001010 c
1)
#2120000
0)
#2125000
b11001011 c
1)
#2130000
0)
#2135000
b11001100 c
1)
#2140000
0)
#2145000
b11001101 c
1)
#2150000
0)
#2155000
b11001110 c
1)
#2160000
0)
#2165000
b11001111 c
1)
#2170000
0)
#2175000
b11010000 c
1)
#2180000
0)
#2185000
b11010001 c
1)
#2190000
0)
#2195000
b11010010 c
1)
#2200000
0)
#2205000
b11010011 c
1)
#2210000
0)
#2215000
b11010100 c
1)
#2220000
0)
#2225000
b11010101 c
1)
#2230000
0)
#2235000
b11010110 c
1)
#2240000
0)
#2245000
b11010111 c
1)
#2250000
0)
#2255000
b11011000 c
1)
#2260000
0)
#2265000
b11011001 c
1)
#2270000
0)
#2275000
b11011010 c
1)
#2280000
0)
#2285000
b11011011 c
1)
#2290000
0)
#2295000
b11011100 c
1)
#2300000
0)
#2305000
b11011101 c
1)
#2310000
0)
#2315000
b11011110 c
1)
#2320000
0)
#2325000
b11011111 c
1)
#2330000
0)
#2335000
b11100000 c
1)
#2340000
0)
#2345000
b11100001 c
1)
#2350000
0)
#2355000
b11100010 c
1)
#2360000
0)
#2365000
b11100011 c
1)
#2370000
0)
#2375000
b11100100 c
1)
#2380000
0)
#2385000
b11100101 c
1)
#2390000
0)
#2395000
b11100110 c
1)
#2400000
0)
#2405000
b11100111 c
1)
#2410000
0)
#2415000
b11101000 c
1)
#2420000
0)
